Workbook

Sheet Orders
A1: order_id | B1: order_date | C1: customer_id | D1: product_category | E1: sales | F1: quantity | G1: profit | H1: discount | I1: Profit Margin | J1: Average Order Value | K1: region | L1: segment | M1: customer_name
A2: ORD0001 | B2: 45957 | C2: CUST028 | D2: Food | E2: 1361.16 | F2: 4 | G2: 197.02 | H2: 0.2 | I2: =G2/E2 -> 0.14474419 | J2: =SUM(E2:E151)/COUNTA(A2:A151) -> 2613.2766 | K2: =VLOOKUP(C2,Customers!A:D,3,FALSE) -> North | L2: =VLOOKUP(C2,Customers!$A:$D,4,FALSE) -> Consumer | M2: =VLOOKUP(C2,Customers!$A:$D,2,FALSE) -> Customer_28
A3: ORD0002 | B3: 45704 | C3: CUST049 | D3: Electronics | E3: 2027.03 | F3: 4 | G3: 339.29 | H3: 0.05 | I3: =G3/E3 -> 0.16738282 | J3: =SUM(E3:E152)/COUNTA(A3:A152) -> 2621.6801 | K3: =VLOOKUP(C3,Customers!A:D,3,FALSE) -> West | L3: =VLOOKUP(C3,Customers!$A:$D,4,FALSE) -> Corporate | M3: =VLOOKUP(C3,Customers!$A:$D,2,FALSE) -> Customer_49
A4: ORD0003 | B4: 45874 | C4: CUST039 | D4: Electronics | E4: 4312.46 | F4: 3 | G4: 1026.45 | H4: 0.05 | I4: =G4/E4 -> 0.2380196 | J4: =SUM(E4:E153)/COUNTA(A4:A153) -> 2625.698 | K4: =VLOOKUP(C4,Customers!A:D,3,FALSE) -> South | L4: =VLOOKUP(C4,Customers!$A:$D,4,FALSE) -> Consumer | M4: =VLOOKUP(C4,Customers!$A:$D,2,FALSE) -> Customer_39
A5: ORD0004 | B5: 45941 | C5: CUST001 | D5: Electronics | E5: 1954.6 | F5: 10 | G5: 297.64 | H5: 0.15 | I5: =G5/E5 -> 0.15227668 | J5: =SUM(E5:E154)/COUNTA(A5:A154) -> 2614.2234 | K5: =VLOOKUP(C5,Customers!A:D,3,FALSE) -> North | L5: =VLOOKUP(C5,Customers!$A:$D,4,FALSE) -> Consumer | M5: =VLOOKUP(C5,Customers!$A:$D,2,FALSE) -> Customer_1
A6: ORD0005 | B6: 45832 | C6: CUST008 | D6: Office Supplies | E6: 3424.47 | F6: 9 | G6: 760.74 | H6: 0.1 | I6: =G6/E6 -> 0.22214824 | J6: =SUM(E6:E155)/COUNTA(A6:A155) -> 2618.7414 | K6: =VLOOKUP(C6,Customers!A:D,3,FALSE) -> South | L6: =VLOOKUP(C6,Customers!$A:$D,4,FALSE) -> Consumer | M6: =VLOOKUP(C6,Customers!$A:$D,2,FALSE) -> Customer_8
A7: ORD0006 | B7: 45792 | C7: CUST033 | D7: Furniture | E7: 2202.09 | F7: 8 | G7: 635.2 | H7: 0 | I7: =G7/E7 -> 0.28845324 | J7: =SUM(E7:E156)/COUNTA(A7:A156) -> 2613.1846 | K7: =VLOOKUP(C7,Customers!A:D,3,FALSE) -> East | L7: =VLOOKUP(C7,Customers!$A:$D,4,FALSE) -> Consumer | M7: =VLOOKUP(C7,Customers!$A:$D,2,FALSE) -> Customer_33
A8: ORD0007 | B8: 45917 | C8: CUST039 | D8: Furniture | E8: 2563.02 | F8: 2 | G8: 616.19 | H8: 0.1 | I8: =G8/E8 -> 0.2404156 | J8: =SUM(E8:E157)/COUNTA(A8:A157) -> 2616.0394 | K8: =VLOOKUP(C8,Customers!A:D,3,FALSE) -> South | L8: =VLOOKUP(C8,Customers!$A:$D,4,FALSE) -> Consumer | M8: =VLOOKUP(C8,Customers!$A:$D,2,FALSE) -> Customer_39
A9: ORD0008 | B9: 45929 | C9: CUST001 | D9: Food | E9: 806.55 | F9: 3 | G9: 200.33 | H9: 0.2 | I9: =G9/E9 -> 0.2483789 | J9: =SUM(E9:E158)/COUNTA(A9:A158) -> 2616.4102 | K9: =VLOOKUP(C9,Customers!A:D,3,FALSE) -> North | L9: =VLOOKUP(C9,Customers!$A:$D,4,FALSE) -> Consumer | M9: =VLOOKUP(C9,Customers!$A:$D,2,FALSE) -> Customer_1
A10: ORD0009 | B10: 45815 | C10: CUST016 | D10: Electronics | E10: 1654.57 | F10: 1 | G10: 467.04 | H10: 0 | I10: =G10/E10 -> 0.28227274 | J10: =SUM(E10:E159)/COUNTA(A10:A159) -> 2629.1557 | K10: =VLOOKUP(C10,Customers!A:D,3,FALSE) -> East | L10: =VLOOKUP(C10,Customers!$A:$D,4,FALSE) -> Consumer | M10: =VLOOKUP(C10,Customers!$A:$D,2,FALSE) -> Customer_16
A11: ORD0010 | B11: 45906 | C11: CUST005 | D11: Food | E11: 1242.31 | F11: 10 | G11: 88.72 | H11: 0 | I11: =G11/E11 -> 0.071415347 | J11: =SUM(E11:E160)/COUNTA(A11:A160) -> 2636.0677 | K11: =VLOOKUP(C11,Customers!A:D,3,FALSE) -> North | L11: =VLOOKUP(C11,Customers!$A:$D,4,FALSE) -> Home Office | M11: =VLOOKUP(C11,Customers!$A:$D,2,FALSE) -> Customer_5
A12: ORD0011 | B12: 45742 | C12: CUST017 | D12: Food | E12: 3840.88 | F12: 3 | G12: 986 | H12: 0.15 | I12: =G12/E12 -> 0.256712 | J12: =SUM(E12:E161)/COUNTA(A12:A161) -> 2646.0231 | K12: =VLOOKUP(C12,Customers!A:D,3,FALSE) -> South | L12: =VLOOKUP(C12,Customers!$A:$D,4,FALSE) -> Corporate | M12: =VLOOKUP(C12,Customers!$A:$D,2,FALSE) -> Customer_17
A13: ORD0012 | B13: 46011 | C13: CUST013 | D13: Office Supplies | E13: 4368.54 | F13: 7 | G13: 1189.24 | H13: 0.05 | I13: =G13/E13 -> 0.27222825 | J13: =SUM(E13:E162)/COUNTA(A13:A162) -> 2637.427 | K13: =VLOOKUP(C13,Customers!A:D,3,FALSE) -> East | L13: =VLOOKUP(C13,Customers!$A:$D,4,FALSE) -> Consumer | M13: =VLOOKUP(C13,Customers!$A:$D,2,FALSE) -> Customer_13
... A151: ORD0150 | B151: 45870 | C151: CUST012 | D151: Furniture | E151: 3675.18 | F151: 2 | G151: 410.44 | H151: 0.1 | I151: =G151/E151 -> 0.11167888 | J151: =SUM(E151:E300)/COUNTA(A151:A300) -> 3675.18 | K151: =VLOOKUP(C151,Customers!A:D,3,FALSE) -> West | L151: =VLOOKUP(C151,Customers!$A:$D,4,FALSE) -> Home Office | M151: =VLOOKUP(C151,Customers!$A:$D,2,FALSE) -> Customer_12

Sheet Customers
A1: customer_id | B1: customer_name | C1: region | D1: segment
A2: CUST001 | B2: Customer_1 | C2: North | D2: Consumer
A3: CUST002 | B3: Customer_2 | C3: East | D3: Consumer
A4: CUST003 | B4: Customer_3 | C4: South | D4: Consumer
A5: CUST004 | B5: Customer_4 | C5: North | D5: Home Office
A6: CUST005 | B6: Customer_5 | C6: North | D6: Home Office
A7: CUST006 | B7: Customer_6 | C7: West | D7: Consumer
A8: CUST007 | B8: Customer_7 | C8: North | D8: Consumer
A9: CUST008 | B9: Customer_8 | C9: South | D9: Consumer
A10: CUST009 | B10: Customer_9 | C10: North | D10: Home Office
A11: CUST010 | B11: Customer_10 | C11: South | D11: Home Office
A12: CUST011 | B12: Customer_11 | C12: West | D12: Consumer
... A51: CUST050 | B51: Customer_50 | C51: West | D51: Consumer

Sheet Dashboard
G1: Excel Advanced Analysis
D2: Sales Analysis by Region and Segment | I2: Monthly sales trend | L2: Top 10 customers
C4: Total sales | D4: Segment | I4: Months | J4: Total sales | L4: Customer_names | M4: Total sales
C5: Region | D5: Consumer | E5: Corporate | F5: Home Office | I5: Jan | J5: 13254.87 | L5: Customer_39 | M5: 25727.48
C6: East | D6: 63077.39 | E6: 18417.31 | F6: 32322.84 | I6: Feb | J6: 42153.67 | L6: Customer_43 | M6: 23892.7
C7: North | D7: 44353.26 | E7: 15311.61 | F7: 26299.05 | I7: Mar | J7: 30454.4 | L7: Customer_50 | M7: 18593.62
C8: South | D8: 49530.07 | E8: 19439.65 | F8: 42425.01 | I8: Apr | J8: 36055.29 | L8: Customer_1 | M8: 17187
C9: West | D9: 41109.88 | E9: 29575.21 | F9: 10130.21 | I9: May | J9: 36672.81 | L9: Customer_15 | M9: 14870.26
I10: Jun | J10: 36667.38 | L10: Customer_25 | M10: 14585.2
D11: Profit Analysis by Category and Region | I11: Jul | J11: 17537.32 | L11: Customer_31 | M11: 14528.55
I12: Aug | J12: 44866.99 | L12: Customer_18 | M12: 13792.91
C13: Total profit | D13: Region | I13: Sep | J13: 28728.08 | L13: Customer_17 | M13: 12924.3
C14: Product Category | D14: East | E14: North | F14: South | G14: West | I14: Oct | J14: 32839.36 | L14: Customer_37 | M14: 12074.44
C15: Clothing | D15: 5180.11 | E15: 2116.71 | F15: 3131.73 | G15: 2175.9 | I15: Nov | J15: 34823.5
C16: Electronics | D16: 6232.42 | E16: 2117.39 | F16: 4576.09 | G16: 2565.61 | I16: Dec | J16: 37937.82
C17: Food | D17: 2147.6 | E17: 3153.4 | F17: 2416.69 | G17: 2486.74
C18: Furniture | D18: 1068.62 | E18: 3368.96 | F18: 3093.94 | G18: 3989.96
C19: Office Supplies | D19: 4691.61 | E19: 1170.09 | F19: 5416.67 | G19: 728.68
